src/__init__.py
src/camera_class.py
src/constants.py
src/device_class.py
src/socket_class.py
src/types.py
src/utils.py
trkir_rpi-0.44.data/scripts/trkir-camera-devices
trkir_rpi-0.44.data/scripts/trkir-camera-run
trkir_rpi-0.44.data/scripts/trkir-install
trkir_rpi-0.44.data/scripts/trkir-rpi-ip
trkir_rpi-0.44.data/scripts/trkir-usb-recycle
trkir_rpi-0.44.dist-info/LICENSE
trkir_rpi-0.44.dist-info/METADATA
trkir_rpi-0.44.dist-info/WHEEL
trkir_rpi-0.44.dist-info/top_level.txt
trkir_rpi-0.44.dist-info/RECORD
