Metadata-Version: 2.1
Name: trkir-rpi
Version: 0.44
Summary: Raspberry PI scripts for PT FLIR and IR cameras
Home-page: https://git.vpa.group/trkir/hardware
Author: VPA.GROUP
Author-email: v.novosad@ivpa.ru
License: UNKNOWN
Platform: UNKNOWN
Classifier: Programming Language :: Python :: 3
Classifier: License :: OSI Approved :: MIT License
Classifier: Operating System :: POSIX :: Linux
